hpo_uq-1.4.0.data/scripts/hyppo
hyppo/__init__.py
hyppo/config.py
hyppo/evaluation.py
hyppo/hyperparams.py
hyppo/obj_fct.py
hyppo/run.py
hyppo/train.py
hyppo/update.py
hyppo/datasets/__init__.py
hyppo/datasets/cifar10.py
hyppo/datasets/custom.py
hyppo/datasets/fake.py
hyppo/datasets/generic.py
hyppo/datasets/loaders.py
hyppo/datasets/network.py
hyppo/datasets/plots.py
hyppo/datasets/utils.py
hyppo/distribution/__init__.py
hyppo/distribution/pytorch.py
hyppo/distribution/tensorflow.py
hyppo/dnnmodels/__init__.py
hyppo/dnnmodels/plots.py
hyppo/dnnmodels/pytorch/__init__.py
hyppo/dnnmodels/pytorch/cnn.py
hyppo/dnnmodels/pytorch/lstm.py
hyppo/dnnmodels/pytorch/mlp.py
hyppo/dnnmodels/pytorch/uq.py
hyppo/dnnmodels/pytorch/utils.py
hyppo/dnnmodels/tensorflow/__init__.py
hyppo/dnnmodels/tensorflow/cnn.py
hyppo/dnnmodels/tensorflow/gcn.py
hyppo/dnnmodels/tensorflow/lstm.py
hyppo/dnnmodels/tensorflow/mlp.py
hyppo/dnnmodels/tensorflow/rnn.py
hyppo/dnnmodels/tensorflow/utils.py
hyppo/sensitivity/__init__.py
hyppo/surrogate/ComputeRBF.py
hyppo/surrogate/InitialRBFMatrices.py
hyppo/surrogate/__init__.py
hyppo/surrogate/gp_opt.py
hyppo/surrogate/phi.py
hyppo/surrogate/rbf_opt.py
hyppo/utils/__init__.py
hyppo/utils/estimator.py
hyppo/utils/extract.py
hyppo/utils/logging.py
hyppo/utils/parallel.py
hyppo/utils/plots.py
hyppo/utils/problems.py
hyppo/utils/sampling.py
hpo_uq-1.4.0.dist-info/LICENSE.txt
hpo_uq-1.4.0.dist-info/METADATA
hpo_uq-1.4.0.dist-info/WHEEL
hpo_uq-1.4.0.dist-info/top_level.txt
hpo_uq-1.4.0.dist-info/RECORD
