Metadata-Version: 2.1
Name: hpo-uq
Version: 1.4.0
Summary: Hyperparameter Optimization Tool using Surrogate Modeling and Uncertainty Quantification.
Home-page: https://hpo-uq.gitlab.io/hyppo
Author: Vincent Dumont
Author-email: vincentdumont11@gmail.com
Maintainer: Vincent Dumont
Maintainer-email: vincentdumont11@gmail.com
Project-URL: Source Code, https://gitlab.com/hpo-uq/hyppo
Classifier: Intended Audience :: Science/Research
Classifier: License :: Other/Proprietary License
Classifier: Natural Language :: English
Classifier: Operating System :: OS Independent
Classifier: Programming Language :: Python
Classifier: Topic :: Scientific/Engineering :: Artificial Intelligence
License-File: LICENSE.txt
Requires-Dist: deap
Requires-Dist: matplotlib
Requires-Dist: numpy
Requires-Dist: pandas
Requires-Dist: pickle5
Requires-Dist: plotly
Requires-Dist: pyyaml
Requires-Dist: SALib
Requires-Dist: scipy
Requires-Dist: sklearn
